syr_lib_hav/__init__.py
syr_lib-0.0.4.dist-info/LICENCE.txt
syr_lib-0.0.4.dist-info/METADATA
syr_lib-0.0.4.dist-info/WHEEL
syr_lib-0.0.4.dist-info/top_level.txt
syr_lib-0.0.4.dist-info/RECORD
