Metadata-Version: 2.1
Name: syr-lib
Version: 0.0.4
Summary: Compute_Haversine
Home-page: UNKNOWN
Author: seshkalyan
Author-email: dseshkalyan@gmail.com
License: SYREN CLOUD TECHNOLOGIES
Platform: UNKNOWN
License-File: LICENCE.txt
